{
  "params": {
    "model": "CPD",
    "L": 4,
    "bond_dim": 64,
    "init_strength": 0.01,
    "bond_prior_alpha": 1.0,
    "added_bias": false,
    "n_epochs": 100,
    "batch_size": 256,
    "patience": 100,
    "min_delta": 0.0001,
    "warmup_epochs": 5,
    "trim_every": 3,
    "trimming_threshold": 0.3,
    "trim_method": "relevance",
    "soft_trim_relaxation": 2
  },
  "seeds": [
    42,
    9536,
    19540,
    42806,
    47659
  ],
  "n_folds": 5,
  "val_ratio": 0.15,
  "datasets": [
    "energy_efficiency"
  ],
  "aggregated": {
    "energy_efficiency": {
      "mean": 0.9968291121941436,
      "std": 0.0004949834152351585,
      "n_runs": 25,
      "min": 0.9958596040430335,
      "max": 0.9978252845307131
    }
  },
  "all_results": [
    {
      "fold": 0,
      "seed": 19540,
      "model": "CPD",
      "dataset": "energy_efficiency",
      "params": {
        "model": "CPD",
        "L": 4,
        "bond_dim": 64,
        "init_strength": 0.01,
        "bond_prior_alpha": 1.0,
        "added_bias": false,
        "n_epochs": 100,
        "batch_size": 256,
        "patience": 100,
        "min_delta": 0.0001,
        "warmup_epochs": 5,
        "trim_every": 3,
        "trimming_threshold": 0.3,
        "trim_method": "relevance",
        "soft_trim_relaxation": 2
      },
      "n_features": 8,
      "n_train": 522,
      "n_val": 92,
      "n_test": 154,
      "train_loss": 0.14227094574251292,
      "train_quality": 0.998595405609466,
      "val_loss": 0.29496237864906305,
      "val_quality": 0.9969643846075947,
      "test_loss": 0.35327217802673905,
      "test_quality": 0.9966535251690477,
      "best_epoch": 7,
      "n_parameters": 2048,
      "elbo_raw": -8858.268160976038,
      "elbo_relative": 113268931.3902335,
      "tau_mean": 3.106397794046266,
      "success": true,
      "singular": false,
      "recovered_from_run": true,
      "run_id": "energy_efficiency-CPD-L4-d64-seed19540-fold0"
    },
    {
      "fold": 1,
      "seed": 19540,
      "model": "CPD",
      "dataset": "energy_efficiency",
      "params": {
        "model": "CPD",
        "L": 4,
        "bond_dim": 64,
        "init_strength": 0.01,
        "bond_prior_alpha": 1.0,
        "added_bias": false,
        "n_epochs": 100,
        "batch_size": 256,
        "patience": 100,
        "min_delta": 0.0001,
        "warmup_epochs": 5,
        "trim_every": 3,
        "trimming_threshold": 0.3,
        "trim_method": "relevance",
        "soft_trim_relaxation": 2
      },
      "n_features": 8,
      "n_train": 522,
      "n_val": 92,
      "n_test": 154,
      "train_loss": 0.18804615625292725,
      "train_quality": 0.9981630148082347,
      "val_loss": 0.24620602826383756,
      "val_quality": 0.9972998734274032,
      "test_loss": 0.24094820681786835,
      "test_quality": 0.9976560529915186,
      "best_epoch": 7,
      "n_parameters": 2048,
      "elbo_raw": -8865.856436970093,
      "elbo_relative": 135030934.55887616,
      "tau_mean": 2.418304576461828,
      "success": true,
      "singular": false,
      "recovered_from_run": true,
      "run_id": "energy_efficiency-CPD-L4-d64-seed19540-fold1"
    },
    {
      "fold": 2,
      "seed": 19540,
      "model": "CPD",
      "dataset": "energy_efficiency",
      "params": {
        "model": "CPD",
        "L": 4,
        "bond_dim": 64,
        "init_strength": 0.01,
        "bond_prior_alpha": 1.0,
        "added_bias": false,
        "n_epochs": 100,
        "batch_size": 256,
        "patience": 100,
        "min_delta": 0.0001,
        "warmup_epochs": 5,
        "trim_every": 3,
        "trimming_threshold": 0.3,
        "trim_method": "relevance",
        "soft_trim_relaxation": 2
      },
      "n_features": 8,
      "n_train": 522,
      "n_val": 92,
      "n_test": 154,
      "train_loss": 0.1794235908268207,
      "train_quality": 0.9982475675169346,
      "val_loss": 0.2591807015959292,
      "val_quality": 0.9973952205682053,
      "test_loss": 0.345353754201532,
      "test_quality": 0.9965155247306345,
      "best_epoch": 7,
      "n_parameters": 2048,
      "elbo_raw": -8736.58124361067,
      "elbo_relative": 123524527.45301007,
      "tau_mean": 2.4204524264936387,
      "success": true,
      "singular": false,
      "recovered_from_run": true,
      "run_id": "energy_efficiency-CPD-L4-d64-seed19540-fold2"
    },
    {
      "fold": 3,
      "seed": 19540,
      "model": "CPD",
      "dataset": "energy_efficiency",
      "params": {
        "model": "CPD",
        "L": 4,
        "bond_dim": 64,
        "init_strength": 0.01,
        "bond_prior_alpha": 1.0,
        "added_bias": false,
        "n_epochs": 100,
        "batch_size": 256,
        "patience": 100,
        "min_delta": 0.0001,
        "warmup_epochs": 5,
        "trim_every": 3,
        "trimming_threshold": 0.3,
        "trim_method": "relevance",
        "soft_trim_relaxation": 2
      },
      "n_features": 8,
      "n_train": 523,
      "n_val": 92,
      "n_test": 153,
      "train_loss": 0.20652312488822283,
      "train_quality": 0.998008727925808,
      "val_loss": 0.2921930715538841,
      "val_quality": 0.9968859209573426,
      "test_loss": 0.3418794515589612,
      "test_quality": 0.9963743193839135,
      "best_epoch": 6,
      "n_parameters": 2048,
      "elbo_raw": -5464.314402168055,
      "elbo_relative": 113674071.47724207,
      "tau_mean": 1.9811533839783626,
      "success": true,
      "singular": false,
      "recovered_from_run": true,
      "run_id": "energy_efficiency-CPD-L4-d64-seed19540-fold3"
    },
    {
      "fold": 4,
      "seed": 19540,
      "model": "CPD",
      "dataset": "energy_efficiency",
      "params": {
        "model": "CPD",
        "L": 4,
        "bond_dim": 64,
        "init_strength": 0.01,
        "bond_prior_alpha": 1.0,
        "added_bias": false,
        "n_epochs": 100,
        "batch_size": 256,
        "patience": 100,
        "min_delta": 0.0001,
        "warmup_epochs": 5,
        "trim_every": 3,
        "trimming_threshold": 0.3,
        "trim_method": "relevance",
        "soft_trim_relaxation": 2
      },
      "n_features": 8,
      "n_train": 523,
      "n_val": 92,
      "n_test": 153,
      "train_loss": 0.1786717031497387,
      "train_quality": 0.9982521105127128,
      "val_loss": 0.2400660892894142,
      "val_quality": 0.9975800334220225,
      "test_loss": 0.2511799863651004,
      "test_quality": 0.9975117159986578,
      "best_epoch": 7,
      "n_parameters": 2048,
      "elbo_raw": -8826.528300540296,
      "elbo_relative": 128778286.60819964,
      "tau_mean": 2.528416421973133,
      "success": true,
      "singular": false,
      "recovered_from_run": true,
      "run_id": "energy_efficiency-CPD-L4-d64-seed19540-fold4"
    },
    {
      "fold": 0,
      "seed": 42,
      "model": "CPD",
      "dataset": "energy_efficiency",
      "params": {
        "model": "CPD",
        "L": 4,
        "bond_dim": 64,
        "init_strength": 0.01,
        "bond_prior_alpha": 1.0,
        "added_bias": false,
        "n_epochs": 100,
        "batch_size": 256,
        "patience": 100,
        "min_delta": 0.0001,
        "warmup_epochs": 5,
        "trim_every": 3,
        "trimming_threshold": 0.3,
        "trim_method": "relevance",
        "soft_trim_relaxation": 2
      },
      "n_features": 8,
      "n_train": 522,
      "n_val": 92,
      "n_test": 154,
      "train_loss": 0.15338082786847634,
      "train_quality": 0.9984601574811381,
      "val_loss": 0.25166921413732996,
      "val_quality": 0.9976751758594551,
      "test_loss": 0.34239889082803354,
      "test_quality": 0.9967150167906799,
      "best_epoch": 7,
      "n_parameters": 2048,
      "elbo_raw": -8874.73190293452,
      "elbo_relative": 109233112.76791652,
      "tau_mean": 2.906795547036059,
      "success": true,
      "singular": false,
      "recovered_from_run": true,
      "run_id": "energy_efficiency-CPD-L4-d64-seed42-fold0"
    },
    {
      "fold": 1,
      "seed": 42,
      "model": "CPD",
      "dataset": "energy_efficiency",
      "params": {
        "model": "CPD",
        "L": 4,
        "bond_dim": 64,
        "init_strength": 0.01,
        "bond_prior_alpha": 1.0,
        "added_bias": false,
        "n_epochs": 100,
        "batch_size": 256,
        "patience": 100,
        "min_delta": 0.0001,
        "warmup_epochs": 5,
        "trim_every": 3,
        "trimming_threshold": 0.3,
        "trim_method": "relevance",
        "soft_trim_relaxation": 2
      },
      "n_features": 8,
      "n_train": 522,
      "n_val": 92,
      "n_test": 154,
      "train_loss": 0.15993776673946655,
      "train_quality": 0.9984126794949184,
      "val_loss": 0.2626158915962564,
      "val_quality": 0.9975557776789787,
      "test_loss": 0.303486681663728,
      "test_quality": 0.9970053801174689,
      "best_epoch": 7,
      "n_parameters": 2048,
      "elbo_raw": -8901.830943794517,
      "elbo_relative": 108432058.81431164,
      "tau_mean": 2.8507508882828034,
      "success": true,
      "singular": false,
      "recovered_from_run": true,
      "run_id": "energy_efficiency-CPD-L4-d64-seed42-fold1"
    },
    {
      "fold": 2,
      "seed": 42,
      "model": "CPD",
      "dataset": "energy_efficiency",
      "params": {
        "model": "CPD",
        "L": 4,
        "bond_dim": 64,
        "init_strength": 0.01,
        "bond_prior_alpha": 1.0,
        "added_bias": false,
        "n_epochs": 100,
        "batch_size": 256,
        "patience": 100,
        "min_delta": 0.0001,
        "warmup_epochs": 5,
        "trim_every": 3,
        "trimming_threshold": 0.3,
        "trim_method": "relevance",
        "soft_trim_relaxation": 2
      },
      "n_features": 8,
      "n_train": 522,
      "n_val": 92,
      "n_test": 154,
      "train_loss": 0.1707465515166931,
      "train_quality": 0.998320418828399,
      "val_loss": 0.2643205277958068,
      "val_quality": 0.9971104574847118,
      "test_loss": 0.35215314506806167,
      "test_quality": 0.9967231815300633,
      "best_epoch": 7,
      "n_parameters": 2048,
      "elbo_raw": -8815.870004535585,
      "elbo_relative": 87130426.79083592,
      "tau_mean": 2.633486322409037,
      "success": true,
      "singular": false,
      "recovered_from_run": true,
      "run_id": "energy_efficiency-CPD-L4-d64-seed42-fold2"
    },
    {
      "fold": 3,
      "seed": 42,
      "model": "CPD",
      "dataset": "energy_efficiency",
      "params": {
        "model": "CPD",
        "L": 4,
        "bond_dim": 64,
        "init_strength": 0.01,
        "bond_prior_alpha": 1.0,
        "added_bias": false,
        "n_epochs": 100,
        "batch_size": 256,
        "patience": 100,
        "min_delta": 0.0001,
        "warmup_epochs": 5,
        "trim_every": 3,
        "trimming_threshold": 0.3,
        "trim_method": "relevance",
        "soft_trim_relaxation": 2
      },
      "n_features": 8,
      "n_train": 523,
      "n_val": 92,
      "n_test": 153,
      "train_loss": 0.1689791117042645,
      "train_quality": 0.9982997532332647,
      "val_loss": 0.1968897001045151,
      "val_quality": 0.998178808818004,
      "test_loss": 0.28850609139298533,
      "test_quality": 0.9972181158715829,
      "best_epoch": 7,
      "n_parameters": 2048,
      "elbo_raw": -8896.067734705353,
      "elbo_relative": 113938819.43548435,
      "tau_mean": 2.723368241550336,
      "success": true,
      "singular": false,
      "recovered_from_run": true,
      "run_id": "energy_efficiency-CPD-L4-d64-seed42-fold3"
    },
    {
      "fold": 4,
      "seed": 42,
      "model": "CPD",
      "dataset": "energy_efficiency",
      "params": {
        "model": "CPD",
        "L": 4,
        "bond_dim": 64,
        "init_strength": 0.01,
        "bond_prior_alpha": 1.0,
        "added_bias": false,
        "n_epochs": 100,
        "batch_size": 256,
        "patience": 100,
        "min_delta": 0.0001,
        "warmup_epochs": 5,
        "trim_every": 3,
        "trimming_threshold": 0.3,
        "trim_method": "relevance",
        "soft_trim_relaxation": 2
      },
      "n_features": 8,
      "n_train": 523,
      "n_val": 92,
      "n_test": 153,
      "train_loss": 0.15276817187316333,
      "train_quality": 0.9985278951382512,
      "val_loss": 0.32389828256396347,
      "val_quality": 0.9970046517628156,
      "test_loss": 0.2759920031015993,
      "test_quality": 0.9968652362945467,
      "best_epoch": 7,
      "n_parameters": 2048,
      "elbo_raw": -8941.809015951707,
      "elbo_relative": 115601196.99159533,
      "tau_mean": 3.018135071462055,
      "success": true,
      "singular": false,
      "recovered_from_run": true,
      "run_id": "energy_efficiency-CPD-L4-d64-seed42-fold4"
    },
    {
      "fold": 0,
      "seed": 42806,
      "model": "CPD",
      "dataset": "energy_efficiency",
      "params": {
        "model": "CPD",
        "L": 4,
        "bond_dim": 64,
        "init_strength": 0.01,
        "bond_prior_alpha": 1.0,
        "added_bias": false,
        "n_epochs": 100,
        "batch_size": 256,
        "patience": 100,
        "min_delta": 0.0001,
        "warmup_epochs": 5,
        "trim_every": 3,
        "trimming_threshold": 0.3,
        "trim_method": "relevance",
        "soft_trim_relaxation": 2
      },
      "n_features": 8,
      "n_train": 522,
      "n_val": 92,
      "n_test": 154,
      "train_loss": 0.15435160792947264,
      "train_quality": 0.9984834591360557,
      "val_loss": 0.24524769451501016,
      "val_quality": 0.9976928181304763,
      "test_loss": 0.4061665605248192,
      "test_quality": 0.9958596040430335,
      "best_epoch": 7,
      "n_parameters": 2048,
      "elbo_raw": -8825.074161794435,
      "elbo_relative": 224354237.5842339,
      "tau_mean": 2.9471710808764433,
      "success": true,
      "singular": false,
      "recovered_from_run": true,
      "run_id": "energy_efficiency-CPD-L4-d64-seed42806-fold0"
    },
    {
      "fold": 1,
      "seed": 42806,
      "model": "CPD",
      "dataset": "energy_efficiency",
      "params": {
        "model": "CPD",
        "L": 4,
        "bond_dim": 64,
        "init_strength": 0.01,
        "bond_prior_alpha": 1.0,
        "added_bias": false,
        "n_epochs": 100,
        "batch_size": 256,
        "patience": 100,
        "min_delta": 0.0001,
        "warmup_epochs": 5,
        "trim_every": 3,
        "trimming_threshold": 0.3,
        "trim_method": "relevance",
        "soft_trim_relaxation": 2
      },
      "n_features": 8,
      "n_train": 522,
      "n_val": 92,
      "n_test": 154,
      "train_loss": 0.2046479031930125,
      "train_quality": 0.9979450706412321,
      "val_loss": 0.29106115709441943,
      "val_quality": 0.9972432277252651,
      "test_loss": 0.36144371179432,
      "test_quality": 0.9965727369762147,
      "best_epoch": 6,
      "n_parameters": 2048,
      "elbo_raw": -5404.024025767735,
      "elbo_relative": 190254288.65645182,
      "tau_mean": 1.849505196805564,
      "success": true,
      "singular": false,
      "recovered_from_run": true,
      "run_id": "energy_efficiency-CPD-L4-d64-seed42806-fold1"
    },
    {
      "fold": 2,
      "seed": 42806,
      "model": "CPD",
      "dataset": "energy_efficiency",
      "params": {
        "model": "CPD",
        "L": 4,
        "bond_dim": 64,
        "init_strength": 0.01,
        "bond_prior_alpha": 1.0,
        "added_bias": false,
        "n_epochs": 100,
        "batch_size": 256,
        "patience": 100,
        "min_delta": 0.0001,
        "warmup_epochs": 5,
        "trim_every": 3,
        "trimming_threshold": 0.3,
        "trim_method": "relevance",
        "soft_trim_relaxation": 2
      },
      "n_features": 8,
      "n_train": 522,
      "n_val": 92,
      "n_test": 154,
      "train_loss": 0.18964614950027806,
      "train_quality": 0.99817443664188,
      "val_loss": 0.2793519211890763,
      "val_quality": 0.9971295038050518,
      "test_loss": 0.30438909941824616,
      "test_quality": 0.9968019840224228,
      "best_epoch": 6,
      "n_parameters": 2048,
      "elbo_raw": -5405.617716663165,
      "elbo_relative": 174950607.76840368,
      "tau_mean": 2.0782648140745423,
      "success": true,
      "singular": false,
      "recovered_from_run": true,
      "run_id": "energy_efficiency-CPD-L4-d64-seed42806-fold2"
    },
    {
      "fold": 3,
      "seed": 42806,
      "model": "CPD",
      "dataset": "energy_efficiency",
      "params": {
        "model": "CPD",
        "L": 4,
        "bond_dim": 64,
        "init_strength": 0.01,
        "bond_prior_alpha": 1.0,
        "added_bias": false,
        "n_epochs": 100,
        "batch_size": 256,
        "patience": 100,
        "min_delta": 0.0001,
        "warmup_epochs": 5,
        "trim_every": 3,
        "trimming_threshold": 0.3,
        "trim_method": "relevance",
        "soft_trim_relaxation": 2
      },
      "n_features": 8,
      "n_train": 523,
      "n_val": 92,
      "n_test": 153,
      "train_loss": 0.1834668688567261,
      "train_quality": 0.9982158959215959,
      "val_loss": 0.6653443952674014,
      "val_quality": 0.9934398073749279,
      "test_loss": 0.2962211572326432,
      "test_quality": 0.9969546230030151,
      "best_epoch": 6,
      "n_parameters": 2048,
      "elbo_raw": -5458.908683002238,
      "elbo_relative": 192403855.92016983,
      "tau_mean": 2.184236327660168,
      "success": true,
      "singular": false,
      "recovered_from_run": true,
      "run_id": "energy_efficiency-CPD-L4-d64-seed42806-fold3"
    },
    {
      "fold": 4,
      "seed": 42806,
      "model": "CPD",
      "dataset": "energy_efficiency",
      "params": {
        "model": "CPD",
        "L": 4,
        "bond_dim": 64,
        "init_strength": 0.01,
        "bond_prior_alpha": 1.0,
        "added_bias": false,
        "n_epochs": 100,
        "batch_size": 256,
        "patience": 100,
        "min_delta": 0.0001,
        "warmup_epochs": 5,
        "trim_every": 3,
        "trimming_threshold": 0.3,
        "trim_method": "relevance",
        "soft_trim_relaxation": 2
      },
      "n_features": 8,
      "n_train": 523,
      "n_val": 92,
      "n_test": 153,
      "train_loss": 0.20755049270346954,
      "train_quality": 0.9978833504264899,
      "val_loss": 0.2229186395093998,
      "val_quality": 0.9978640525819552,
      "test_loss": 0.3297775819637451,
      "test_quality": 0.9969544101026832,
      "best_epoch": 7,
      "n_parameters": 2048,
      "elbo_raw": -8744.304177016942,
      "elbo_relative": 199172030.87667,
      "tau_mean": 2.1884484073451396,
      "success": true,
      "singular": false,
      "recovered_from_run": true,
      "run_id": "energy_efficiency-CPD-L4-d64-seed42806-fold4"
    },
    {
      "fold": 0,
      "seed": 47659,
      "model": "CPD",
      "dataset": "energy_efficiency",
      "params": {
        "model": "CPD",
        "L": 4,
        "bond_dim": 64,
        "init_strength": 0.01,
        "bond_prior_alpha": 1.0,
        "added_bias": false,
        "n_epochs": 100,
        "batch_size": 256,
        "patience": 100,
        "min_delta": 0.0001,
        "warmup_epochs": 5,
        "trim_every": 3,
        "trimming_threshold": 0.3,
        "trim_method": "relevance",
        "soft_trim_relaxation": 2
      },
      "n_features": 8,
      "n_train": 522,
      "n_val": 92,
      "n_test": 154,
      "train_loss": 0.1833942687065387,
      "train_quality": 0.9981801671367629,
      "val_loss": 0.23031163908910282,
      "val_quality": 0.997754364754554,
      "test_loss": 0.336666343649347,
      "test_quality": 0.9967695745163959,
      "best_epoch": 5,
      "n_parameters": 2048,
      "elbo_raw": -4674.656660425798,
      "elbo_relative": 162344124.1555206,
      "tau_mean": 1.7768517690621284,
      "success": true,
      "singular": false,
      "recovered_from_run": true,
      "run_id": "energy_efficiency-CPD-L4-d64-seed47659-fold0"
    },
    {
      "fold": 1,
      "seed": 47659,
      "model": "CPD",
      "dataset": "energy_efficiency",
      "params": {
        "model": "CPD",
        "L": 4,
        "bond_dim": 64,
        "init_strength": 0.01,
        "bond_prior_alpha": 1.0,
        "added_bias": false,
        "n_epochs": 100,
        "batch_size": 256,
        "patience": 100,
        "min_delta": 0.0001,
        "warmup_epochs": 5,
        "trim_every": 3,
        "trimming_threshold": 0.3,
        "trim_method": "relevance",
        "soft_trim_relaxation": 2
      },
      "n_features": 8,
      "n_train": 522,
      "n_val": 92,
      "n_test": 154,
      "train_loss": 0.18592767267297342,
      "train_quality": 0.9981621623054593,
      "val_loss": 0.2317038318698512,
      "val_quality": 0.9974894137637292,
      "test_loss": 0.40666887410557884,
      "test_quality": 0.9962514675627822,
      "best_epoch": 6,
      "n_parameters": 2048,
      "elbo_raw": -5378.215298823343,
      "elbo_relative": 157884029.2679683,
      "tau_mean": 1.9068017124877341,
      "success": true,
      "singular": false,
      "recovered_from_run": true,
      "run_id": "energy_efficiency-CPD-L4-d64-seed47659-fold1"
    },
    {
      "fold": 2,
      "seed": 47659,
      "model": "CPD",
      "dataset": "energy_efficiency",
      "params": {
        "model": "CPD",
        "L": 4,
        "bond_dim": 64,
        "init_strength": 0.01,
        "bond_prior_alpha": 1.0,
        "added_bias": false,
        "n_epochs": 100,
        "batch_size": 256,
        "patience": 100,
        "min_delta": 0.0001,
        "warmup_epochs": 5,
        "trim_every": 3,
        "trimming_threshold": 0.3,
        "trim_method": "relevance",
        "soft_trim_relaxation": 2
      },
      "n_features": 8,
      "n_train": 522,
      "n_val": 92,
      "n_test": 154,
      "train_loss": 0.17885825372861566,
      "train_quality": 0.9982562087866744,
      "val_loss": 0.3479354726823177,
      "val_quality": 0.9965263491326635,
      "test_loss": 0.21540093472029817,
      "test_quality": 0.9978252845307131,
      "best_epoch": 7,
      "n_parameters": 2048,
      "elbo_raw": -8765.98213701695,
      "elbo_relative": 168723703.43416324,
      "tau_mean": 2.444846591964189,
      "success": true,
      "singular": false,
      "recovered_from_run": true,
      "run_id": "energy_efficiency-CPD-L4-d64-seed47659-fold2"
    },
    {
      "fold": 3,
      "seed": 47659,
      "model": "CPD",
      "dataset": "energy_efficiency",
      "params": {
        "model": "CPD",
        "L": 4,
        "bond_dim": 64,
        "init_strength": 0.01,
        "bond_prior_alpha": 1.0,
        "added_bias": false,
        "n_epochs": 100,
        "batch_size": 256,
        "patience": 100,
        "min_delta": 0.0001,
        "warmup_epochs": 5,
        "trim_every": 3,
        "trimming_threshold": 0.3,
        "trim_method": "relevance",
        "soft_trim_relaxation": 2
      },
      "n_features": 8,
      "n_train": 523,
      "n_val": 92,
      "n_test": 153,
      "train_loss": 0.181702166322183,
      "train_quality": 0.9982570978963107,
      "val_loss": 0.26469644874720943,
      "val_quality": 0.9971182239744346,
      "test_loss": 0.3230864219617932,
      "test_quality": 0.9967108762838498,
      "best_epoch": 7,
      "n_parameters": 2048,
      "elbo_raw": -8806.220296033238,
      "elbo_relative": 169945036.44619915,
      "tau_mean": 2.4957363850543435,
      "success": true,
      "singular": false,
      "recovered_from_run": true,
      "run_id": "energy_efficiency-CPD-L4-d64-seed47659-fold3"
    },
    {
      "fold": 4,
      "seed": 47659,
      "model": "CPD",
      "dataset": "energy_efficiency",
      "params": {
        "model": "CPD",
        "L": 4,
        "bond_dim": 64,
        "init_strength": 0.01,
        "bond_prior_alpha": 1.0,
        "added_bias": false,
        "n_epochs": 100,
        "batch_size": 256,
        "patience": 100,
        "min_delta": 0.0001,
        "warmup_epochs": 5,
        "trim_every": 3,
        "trimming_threshold": 0.3,
        "trim_method": "relevance",
        "soft_trim_relaxation": 2
      },
      "n_features": 8,
      "n_train": 523,
      "n_val": 92,
      "n_test": 153,
      "train_loss": 0.15712324969796873,
      "train_quality": 0.998446973090919,
      "val_loss": 0.35562339190119896,
      "val_quality": 0.9968076195822851,
      "test_loss": 0.38156286111575827,
      "test_quality": 0.9960854785798593,
      "best_epoch": 7,
      "n_parameters": 2048,
      "elbo_raw": -8723.192235882441,
      "elbo_relative": 154173892.8993706,
      "tau_mean": 2.632525812410608,
      "success": true,
      "singular": false,
      "recovered_from_run": true,
      "run_id": "energy_efficiency-CPD-L4-d64-seed47659-fold4"
    },
    {
      "fold": 0,
      "seed": 9536,
      "model": "CPD",
      "dataset": "energy_efficiency",
      "params": {
        "model": "CPD",
        "L": 4,
        "bond_dim": 64,
        "init_strength": 0.01,
        "bond_prior_alpha": 1.0,
        "added_bias": false,
        "n_epochs": 100,
        "batch_size": 256,
        "patience": 100,
        "min_delta": 0.0001,
        "warmup_epochs": 5,
        "trim_every": 3,
        "trimming_threshold": 0.3,
        "trim_method": "relevance",
        "soft_trim_relaxation": 2
      },
      "n_features": 8,
      "n_train": 522,
      "n_val": 92,
      "n_test": 154,
      "train_loss": 0.14455986845400323,
      "train_quality": 0.9985645143221124,
      "val_loss": 0.3128797371314964,
      "val_quality": 0.9967903467843227,
      "test_loss": 0.3047250659478351,
      "test_quality": 0.9971521784910622,
      "best_epoch": 7,
      "n_parameters": 2048,
      "elbo_raw": -8787.293480102744,
      "elbo_relative": 99379729.69243143,
      "tau_mean": 2.9379576672467427,
      "success": true,
      "singular": false,
      "recovered_from_run": true,
      "run_id": "energy_efficiency-CPD-L4-d64-seed9536-fold0"
    },
    {
      "fold": 1,
      "seed": 9536,
      "model": "CPD",
      "dataset": "energy_efficiency",
      "params": {
        "model": "CPD",
        "L": 4,
        "bond_dim": 64,
        "init_strength": 0.01,
        "bond_prior_alpha": 1.0,
        "added_bias": false,
        "n_epochs": 100,
        "batch_size": 256,
        "patience": 100,
        "min_delta": 0.0001,
        "warmup_epochs": 5,
        "trim_every": 3,
        "trimming_threshold": 0.3,
        "trim_method": "relevance",
        "soft_trim_relaxation": 2
      },
      "n_features": 8,
      "n_train": 522,
      "n_val": 92,
      "n_test": 154,
      "train_loss": 0.2076312779358289,
      "train_quality": 0.9979666124693088,
      "val_loss": 0.4108331552401293,
      "val_quality": 0.9950560579984703,
      "test_loss": 0.266501125153519,
      "test_quality": 0.9975093006645067,
      "best_epoch": 7,
      "n_parameters": 2048,
      "elbo_raw": -8812.383592714668,
      "elbo_relative": 106322144.70958808,
      "tau_mean": 2.210709413389071,
      "success": true,
      "singular": false,
      "recovered_from_run": true,
      "run_id": "energy_efficiency-CPD-L4-d64-seed9536-fold1"
    },
    {
      "fold": 2,
      "seed": 9536,
      "model": "CPD",
      "dataset": "energy_efficiency",
      "params": {
        "model": "CPD",
        "L": 4,
        "bond_dim": 64,
        "init_strength": 0.01,
        "bond_prior_alpha": 1.0,
        "added_bias": false,
        "n_epochs": 100,
        "batch_size": 256,
        "patience": 100,
        "min_delta": 0.0001,
        "warmup_epochs": 5,
        "trim_every": 3,
        "trimming_threshold": 0.3,
        "trim_method": "relevance",
        "soft_trim_relaxation": 2
      },
      "n_features": 8,
      "n_train": 522,
      "n_val": 92,
      "n_test": 154,
      "train_loss": 0.15311169971784,
      "train_quality": 0.9984580766526414,
      "val_loss": 0.31200157833482145,
      "val_quality": 0.9971669941562586,
      "test_loss": 0.4222025362070628,
      "test_quality": 0.9959568499437998,
      "best_epoch": 7,
      "n_parameters": 2048,
      "elbo_raw": -8786.464436638624,
      "elbo_relative": 94670416.96761134,
      "tau_mean": 2.8933955577677954,
      "success": true,
      "singular": false,
      "recovered_from_run": true,
      "run_id": "energy_efficiency-CPD-L4-d64-seed9536-fold2"
    },
    {
      "fold": 3,
      "seed": 9536,
      "model": "CPD",
      "dataset": "energy_efficiency",
      "params": {
        "model": "CPD",
        "L": 4,
        "bond_dim": 64,
        "init_strength": 0.01,
        "bond_prior_alpha": 1.0,
        "added_bias": false,
        "n_epochs": 100,
        "batch_size": 256,
        "patience": 100,
        "min_delta": 0.0001,
        "warmup_epochs": 5,
        "trim_every": 3,
        "trimming_threshold": 0.3,
        "trim_method": "relevance",
        "soft_trim_relaxation": 2
      },
      "n_features": 8,
      "n_train": 523,
      "n_val": 92,
      "n_test": 153,
      "train_loss": 0.18425347110569326,
      "train_quality": 0.9982069691430889,
      "val_loss": 0.34799132091999024,
      "val_quality": 0.9969381403336823,
      "test_loss": 0.2854542260278743,
      "test_quality": 0.996845216078157,
      "best_epoch": 6,
      "n_parameters": 2048,
      "elbo_raw": -5417.275067050257,
      "elbo_relative": 106492615.79050955,
      "tau_mean": 2.0932259959882207,
      "success": true,
      "singular": false,
      "recovered_from_run": true,
      "run_id": "energy_efficiency-CPD-L4-d64-seed9536-fold3"
    },
    {
      "fold": 4,
      "seed": 9536,
      "model": "CPD",
      "dataset": "energy_efficiency",
      "params": {
        "model": "CPD",
        "L": 4,
        "bond_dim": 64,
        "init_strength": 0.01,
        "bond_prior_alpha": 1.0,
        "added_bias": false,
        "n_epochs": 100,
        "batch_size": 256,
        "patience": 100,
        "min_delta": 0.0001,
        "warmup_epochs": 5,
        "trim_every": 3,
        "trimming_threshold": 0.3,
        "trim_method": "relevance",
        "soft_trim_relaxation": 2
      },
      "n_features": 8,
      "n_train": 523,
      "n_val": 92,
      "n_test": 153,
      "train_loss": 0.16751287790731567,
      "train_quality": 0.998357721447602,
      "val_loss": 0.26388583269150195,
      "val_quality": 0.9974334456347209,
      "test_loss": 0.26753632664746524,
      "test_quality": 0.9972401511769818,
      "best_epoch": 6,
      "n_parameters": 2048,
      "elbo_raw": -5376.30553071489,
      "elbo_relative": 97028871.3684495,
      "tau_mean": 2.2956852210460554,
      "success": true,
      "singular": false,
      "recovered_from_run": true,
      "run_id": "energy_efficiency-CPD-L4-d64-seed9536-fold4"
    }
  ]
}